{
  "Schema": "sales",
  "Name": "countryregioncurrency",
  "Columns": [
    {
      "Name": "countryregioncode",
      "DataType": "varchar(3)",
      "Nullable": false,
      "Generated": "NEVER",
      "Virtual": false,
      "Storage": "EXTENDED",
      "Compression": "DEFAULT",
      "ShouldApplyExpression": "",
      "OldName": ""
    },
    {
      "Name": "currencycode",
      "DataType": "CHAR(3)",
      "Nullable": false,
      "Generated": "NEVER",
      "Virtual": false,
      "Storage": "EXTENDED",
      "Compression": "DEFAULT",
      "ShouldApplyExpression": "",
      "OldName": ""
    },
    {
      "Name": "modifieddate",
      "DataType": "timestamp",
      "Nullable": false,
      "Default": "now()",
      "Generated": "NEVER",
      "Virtual": false,
      "Storage": "PLAIN",
      "Compression": "DEFAULT",
      "ShouldApplyExpression": "",
      "OldName": ""
    }
  ],
  "Indexes": [
    {
      "Name": "PK_CountryRegionCurrency_CountryRegionCode_CurrencyCode",
      "PrimaryKey": true,
      "Unique": true,
      "UniqueConstraint": false,
      "Clustered": true,
      "IndexColumns": "countryregioncode,currencycode",
      "AccessMethod": "btree",
      "ShouldApplyExpression": "",
      "FillFactor": 90,
      "NullsNotDistinct": false,
      "Deferrable": false,
      "InitiallyDeferred": false,
      "UpdateFillFactor": false
    }
  ],
  "ForeignKeys": [
    {
      "Name": "FK_CountryRegionCurrency_CountryRegion_CountryRegionCode",
      "Columns": "countryregioncode",
      "RelatedTableSchema": "person",
      "RelatedTable": "countryregion",
      "RelatedColumns": "countryregioncode",
      "ShouldApplyExpression": "",
      "DeleteAction": "",
      "UpdateAction": "",
      "Deferrable": false,
      "InitiallyDeferred": false,
      "MatchType": "SIMPLE"
    },
    {
      "Name": "FK_CountryRegionCurrency_Currency_CurrencyCode",
      "Columns": "currencycode",
      "RelatedTableSchema": "sales",
      "RelatedTable": "currency",
      "RelatedColumns": "currencycode",
      "ShouldApplyExpression": "",
      "DeleteAction": "",
      "UpdateAction": "",
      "Deferrable": false,
      "InitiallyDeferred": false,
      "MatchType": "SIMPLE"
    }
  ],
  "CheckConstraints": [],
  "Statistics": [],
  "ExcludeConstraints": [],
  "ShouldApplyExpression": "",
  "ContentFile": "",
  "MergeType": "NONE",
  "MergeDisableTriggers": false,
  "MergeDisableRules": false,
  "MergeUpdateDescendents": true,
  "OldName": "",
  "RowLevelSecurity": false,
  "ForceRowLevelSecurity": false,
  "AccessMethod": "heap",
  "PersistenceType": "Logged",
  "UpdateFillFactor": false,
  "FillFactor": 100
}