{
  "Schema": "public",
  "Name": "address",
  "Columns": [
    {
      "Name": "address",
      "DataType": "varchar(50)",
      "Nullable": false,
      "Generated": "NEVER",
      "Virtual": true,
      "Storage": "EXTENDED",
      "Compression": "DEFAULT",
      "ShouldApplyExpression": "",
      "OldName": ""
    },
    {
      "Name": "address2",
      "DataType": "varchar(50)",
      "Nullable": true,
      "Generated": "NEVER",
      "Virtual": true,
      "Storage": "EXTENDED",
      "Compression": "DEFAULT",
      "ShouldApplyExpression": "",
      "OldName": ""
    },
    {
      "Name": "address_id",
      "DataType": "int4",
      "Nullable": false,
      "Default": "nextval('address_address_id_seq'::regclass)",
      "Generated": "NEVER",
      "Virtual": true,
      "Storage": "PLAIN",
      "Compression": "DEFAULT",
      "ShouldApplyExpression": "",
      "OldName": ""
    },
    {
      "Name": "city_id",
      "DataType": "int2",
      "Nullable": false,
      "Generated": "NEVER",
      "Virtual": true,
      "Storage": "PLAIN",
      "Compression": "DEFAULT",
      "ShouldApplyExpression": "",
      "OldName": ""
    },
    {
      "Name": "district",
      "DataType": "varchar(20)",
      "Nullable": false,
      "Generated": "NEVER",
      "Virtual": true,
      "Storage": "EXTENDED",
      "Compression": "DEFAULT",
      "ShouldApplyExpression": "",
      "OldName": ""
    },
    {
      "Name": "last_update",
      "DataType": "timestamp",
      "Nullable": false,
      "Default": "now()",
      "Generated": "NEVER",
      "Virtual": true,
      "Storage": "PLAIN",
      "Compression": "DEFAULT",
      "ShouldApplyExpression": "",
      "OldName": ""
    },
    {
      "Name": "phone",
      "DataType": "varchar(20)",
      "Nullable": false,
      "Generated": "NEVER",
      "Virtual": true,
      "Storage": "EXTENDED",
      "Compression": "DEFAULT",
      "ShouldApplyExpression": "",
      "OldName": ""
    },
    {
      "Name": "postal_code",
      "DataType": "varchar(10)",
      "Nullable": true,
      "Generated": "NEVER",
      "Virtual": true,
      "Storage": "EXTENDED",
      "Compression": "DEFAULT",
      "ShouldApplyExpression": "",
      "OldName": ""
    }
  ],
  "Indexes": [
    {
      "Name": "address_pkey",
      "PrimaryKey": true,
      "Unique": true,
      "UniqueConstraint": false,
      "Clustered": false,
      "IndexColumns": "address_id",
      "AccessMethod": "btree",
      "ShouldApplyExpression": "",
      "FillFactor": 90,
      "NullsNotDistinct": false,
      "Deferrable": false,
      "InitiallyDeferred": false,
      "UpdateFillFactor": false,
      "Inherit": false
    },
    {
      "Name": "idx_fk_city_id",
      "PrimaryKey": false,
      "Unique": false,
      "UniqueConstraint": false,
      "Clustered": false,
      "IndexColumns": "city_id",
      "AccessMethod": "btree",
      "ShouldApplyExpression": "",
      "FillFactor": 90,
      "NullsNotDistinct": false,
      "Deferrable": false,
      "InitiallyDeferred": false,
      "UpdateFillFactor": false,
      "Inherit": false
    }
  ],
  "ForeignKeys": [
    {
      "Name": "fk_address_city",
      "Columns": "city_id",
      "RelatedTableSchema": "public",
      "RelatedTable": "city",
      "RelatedColumns": "city_id",
      "ShouldApplyExpression": "",
      "DeleteAction": "",
      "UpdateAction": "",
      "Deferrable": false,
      "InitiallyDeferred": false,
      "MatchType": "SIMPLE"
    }
  ],
  "CheckConstraints": [],
  "Statistics": [],
  "ExcludeConstraints": [],
  "ShouldApplyExpression": "",
  "ContentFile": "Table Contents/public.address.tabledata",
  "MergeType": "Insert/Update",
  "MatchColumns": "",
  "MergeFilter": "",
  "MergeDisableTriggers": false,
  "MergeDisableRules": false,
  "MergeUpdateDescendents": false,
  "OldName": "",
  "RowLevelSecurity": false,
  "ForceRowLevelSecurity": false,
  "AccessMethod": "heap",
  "PersistenceType": "Logged",
  "UpdateFillFactor": false,
  "FillFactor": 100
}